{
  "version": "7",
  "dialect": "postgresql",
  "entries": [
    {
      "idx": 0,
      "version": "7",
      "when": 1776211200000,
      "tag": "0000_baseline",
      "breakpoints": true
    },
    {
      "idx": 1,
      "version": "7",
      "when": 1776211201000,
      "tag": "0001_schema_changes",
      "breakpoints": true
    },
    {
      "idx": 2,
      "version": "7",
      "when": 1776396834750,
      "tag": "0002_add_vendor_contact_fields",
      "breakpoints": true
    },
    {
      "idx": 3,
      "version": "7",
      "when": 1776397419169,
      "tag": "0003_add_orders_fields_and_recycling_orders",
      "breakpoints": true
    },
    {
      "idx": 4,
      "version": "7",
      "when": 1776404136521,
      "tag": "0004_orders_customer_contacts_to_jsonb",
      "breakpoints": true
    },
    {
      "idx": 5,
      "version": "7",
      "when": 1776705839150,
      "tag": "0005_complete_tiger_shark",
      "breakpoints": true
    },
    {
      "idx": 6,
      "version": "7",
      "when": 1776743189859,
      "tag": "0006_unusual_big_bertha",
      "breakpoints": true
    },
    {
      "idx": 7,
      "version": "7",
      "when": 1776881652178,
      "tag": "0007_daily_hammerhead",
      "breakpoints": true
    },
    {
      "idx": 8,
      "version": "7",
      "when": 1776888225270,
      "tag": "0008_simple_the_twelve",
      "breakpoints": true
    },
    {
      "idx": 9,
      "version": "7",
      "when": 1776892430399,
      "tag": "0009_dry_gamora",
      "breakpoints": true
    },
    {
      "idx": 10,
      "version": "7",
      "when": 1745366400000,
      "tag": "0010_auth_user_sync_trigger",
      "breakpoints": true
    }
  ]
}